procaaso_seams_sdk/__init__.py
procaaso_seams_sdk/bus/__init__.py
procaaso_seams_sdk/bus/client.py
procaaso_seams_sdk/bus/envelopes.py
procaaso_seams_sdk/bus/idempotency.py
procaaso_seams_sdk/bus/polling_router.py
procaaso_seams_sdk/bus/router.py
procaaso_seams_sdk/logging/__init__.py
procaaso_seams_sdk/logging/errors.py
procaaso_seams_sdk/seams/__init__.py
procaaso_seams_sdk/seams/models.py
procaaso_seams_sdk/seams/store.py
procaaso_seams_sdk/seams/validators.py
procaaso_seams_sdk/services/__init__.py
procaaso_seams_sdk/services/actuator.py
procaaso_seams_sdk/services/app.py
procaaso_seams_sdk/services/base.py
procaaso_seams_sdk/services/driver.py
procaaso_seams_sdk/services/sensor.py
procaaso_seams_sdk/services/unit.py
procaaso_seams_sdk/sidecar/__init__.py
procaaso_seams_sdk/sidecar/adapter.py
procaaso_seams_sdk/sidecar/client.py
procaaso_seams_sdk/sidecar/factory.py
procaaso_seams_sdk/sidecar/store.py
procaaso_seams_sdk-1.0.3.dist-info/METADATA
procaaso_seams_sdk-1.0.3.dist-info/WHEEL
procaaso_seams_sdk-1.0.3.dist-info/RECORD
