Metadata-Version: 2.1
Name: procaaso-seams-sdk
Version: 1.0.3
Summary: Interface Wrapper to allow event-based communication between containers via sidecar ENS
Author: Brandon Smith
Author-email: bsmith@consynsys.com
Requires-Python: >=3.10,<4.0
Classifier: Programming Language :: Python :: 3
Classifier: Programming Language :: Python :: 3.10
Classifier: Programming Language :: Python :: 3.11
Classifier: Programming Language :: Python :: 3.12
Requires-Dist: aiohttp (>=3.9.0,<4.0.0)
Requires-Dist: procaaso-client (>=0.1.19,<0.2.0)
Requires-Dist: procaaso-log (>=0.3.3,<0.4.0)
Requires-Dist: procaaso-state-machine (>=0.0.3,<0.0.4)
Requires-Dist: pydantic (>=1.10.0,<2.0.0)
